MANIFEST.in
README.rst
setup.py
aliyun_python_sdk_visionai_poc.egg-info/PKG-INFO
aliyun_python_sdk_visionai_poc.egg-info/SOURCES.txt
aliyun_python_sdk_visionai_poc.egg-info/dependency_links.txt
aliyun_python_sdk_visionai_poc.egg-info/requires.txt
aliyun_python_sdk_visionai_poc.egg-info/top_level.txt
aliyunsdkvisionai_poc/__init__.py
aliyunsdkvisionai_poc/request/__init__.py
aliyunsdkvisionai_poc/request/v20200408/CheckMultiagentRequest.py
aliyunsdkvisionai_poc/request/v20200408/PredictCategoryRequest.py
aliyunsdkvisionai_poc/request/v20200408/RecognizeCarRequest.py
aliyunsdkvisionai_poc/request/v20200408/RecognizeEntityRequest.py
aliyunsdkvisionai_poc/request/v20200408/RecognizeFlowerRequest.py
aliyunsdkvisionai_poc/request/v20200408/RecognizeLabelRequest.py
aliyunsdkvisionai_poc/request/v20200408/RecognizePetRequest.py
aliyunsdkvisionai_poc/request/v20200408/__init__.py